my_school_menus/__init__.py
my_school_menus/__meta__.py
my_school_menus/api.py
my_school_menus/calendar.py
my_school_menus-0.0.6.dist-info/METADATA
my_school_menus-0.0.6.dist-info/WHEEL
my_school_menus-0.0.6.dist-info/licenses/LICENSE
my_school_menus-0.0.6.dist-info/RECORD
