Metadata-Version: 2.3
Name: my-school-menus
Version: 0.0.6
Summary: A package for interacting with My School Menus.
Project-URL: Homepage, https://github.com/andrewdefilippis/my_school_menus
Project-URL: Issues, https://github.com/andrewdefilippis/my_school_menus/issues
Author-email: "Andrew R. DeFilippis" <andrew@defilippisfamily.com>
License: MIT License
License-File: LICENSE
Keywords: api,calendar,lunch,menu,school
Classifier: License :: OSI Approved :: MIT License
Classifier: Operating System :: OS Independent
Classifier: Programming Language :: Python :: 3
Requires-Python: >=3.9
Requires-Dist: icalendar~=5.0.11
Requires-Dist: requests<2.33,>=2.31
Provides-Extra: test
Requires-Dist: pytest~=7.4.3; extra == 'test'
